<?xml version="1.0"?>
<gameList>
	<game>
		<path>./PPSSPP.sh</path>
		<name>PPSSPP</name>
		<desc>A standalone emulator for PlayStation Portable (PSP).</desc>
		<image>./images/ppsspp-image.png</image>
		<thumbnail>./images/ppsspp-logo.png</thumbnail>
		<marquee>./images/ppsspp-logo.png</marquee>
		<genre>Emulator</genre>
		<lang>en</lang>
	</game>
	<game>
		<path>./ScummVM.sh</path>
		<name>ScummVM</name>
		<desc>A framework for running several classic point and click adventures.</desc>
		<image>./images/scummvm-image.png</image>
		<thumbnail>./images/scummvm-logo.png</thumbnail>
		<marquee>./images/scummvm-logo.png</marquee>
		<genre>Emulator</genre>
		<lang>en</lang>
	</game>
	<game>
		<path>./Flycast.sh</path>
		<name>Flycast</name>
		<desc>A standalone emulator for Dreamcast.</desc>
		<image>./images/flycast-image.png</image>
		<thumbnail>./images/flycast-logo.png</thumbnail>
		<marquee>./images/flycast-logo.png</marquee>
		<genre>Emulator</genre>
		<lang>en</lang>
	</game>
	<game>
		<path>./RetroArch.sh</path>
		<name>RetroArch</name>
		<desc>A collection of various emulators and game engines.</desc>
		<image>./images/retroarch-image.png</image>
		<thumbnail>./images/retroarch-logo.png</thumbnail>
		<marquee>./images/retroarch-logo.png</marquee>
		<genre>Emulator</genre>
		<lang>en</lang>
	</game>
</gameList>
